{
  "00434867c728e095f7a94df21e0112b1767a7801.png": {
    "title": "foodhsaring-white.png",
    "description": "foodhsaring main",
    "tags": []
  },
  "1e7a177ac4987b857279159b700a4109a5db10e7.png": {
    "title": "world-practices general.png",
    "description": "practices general\r\n",
    "tags": []
  },
  "31783286c793341b219d335081a50fcc62075879.PNG": {
    "title": "Slides Screenshot.PNG",
    "description": "RE slide screenshot",
    "tags": []
  },
  "933c130fc386da55cfc983689c7ddf9460069574.png": {
    "title": "RE - Lecture title frames-16.png",
    "description": "Exercise frame",
    "tags": []
  },
  "737c964aa40b0b0e044a9e8f4e2d3e962c020434.png": {
    "title": "RE - Lecture title frames-15.png",
    "description": "lecture slide",
    "tags": []
  },
  "b46de93d68ec998199fbe3849154af72ef4c26e8.png": {
    "title": "RE - Lecture title frames-10.png",
    "description": "RE 0 frame",
    "tags": []
  },
  "3cd83275ed70a08c787dd69f174b9ff4f8b5950c.png": {
    "title": "RE - Lecture title frames-01.png",
    "description": "RE 1 frame",
    "tags": []
  },
  "c0985a86bf6e95182fc52f80989079c3d3a86ee6.png": {
    "title": "RE - Lecture title frames-02.png",
    "description": "Re 2 slide",
    "tags": []
  },
  "4b28fe60323e6b426d958b885c2c10a721afa62f.png": {
    "title": "RE - Lecture title frames-03.png",
    "description": "RE 3 frame",
    "tags": []
  },
  "6ea2880177e0f770aa6881de5c4527cdb0287010.png": {
    "title": "RE - Lecture title frames-04.png",
    "description": "RE 4 slide",
    "tags": []
  },
  "51cc6567c5c9a6b2b2583e86e6eada7f85fe8891.png": {
    "title": "RE - Lecture title frames-05.png",
    "description": "RE 5 frame",
    "tags": []
  },
  "1b91ec0a5b59794c5814ba5b2304808924b1d296.png": {
    "title": "RE - Lecture title frames-06.png",
    "description": "RE 6 slide",
    "tags": []
  },
  "7f52b1bddf6c09e5b99289bfa69ff0e554b12d6f.png": {
    "title": "RE - Lecture title frames-07.png",
    "description": "RE 7 slide",
    "tags": []
  },
  "8524e2473de12975920c8a6452fac0eab95bf965.png": {
    "title": "RE - Lecture title frames-08.png",
    "description": "RE 8 slide",
    "tags": []
  },
  "1192bfe762ae118ece5e104b3c4326f40396308d.png": {
    "title": "RE - Lecture title frames-09.png",
    "description": "RE 9 frame",
    "tags": []
  },
  "c2e5649cf0e6787b3dcd1ce41a888e862ed7586d.png": {
    "title": "aggregation.png",
    "description": "Aggregation",
    "tags": []
  },
  "0493e4fa8e58eaf5e21e7ea793f538756b1bea1d.png": {
    "title": "association.png",
    "description": "association",
    "tags": []
  },
  "5621e2911b21c352499d791f24e9e2ee30f21c80.png": {
    "title": "compositon.png",
    "description": "composition",
    "tags": []
  },
  "f032b552d30e6e3216c3681566d4fa26131febe9.png": {
    "title": "dependency.png",
    "description": "depend3ncy",
    "tags": []
  },
  "6d7d3fd1ef330b13240c96f6b456868a23075e48.png": {
    "title": "inheritance.png",
    "description": "inheritance",
    "tags": []
  },
  "21fe0760e80e2705564a9396c9584fa0c33d6a99.png": {
    "title": "realization.png",
    "description": "realization",
    "tags": []
  },
  "66f4ed424f32304b0b86e14f6e2e5b340615e47a.png": {
    "title": "etce-logo entwurf-05.png",
    "description": "RE header",
    "tags": []
  },
  "fdc6ff36b564f1d9e2b4498672f4fea73823d7fd.png": {
    "title": "RE Processes Overview.png",
    "description": "RE process",
    "tags": []
  },
  "80c7ffd206c926fec5180622720ce9a53f885119.png": {
    "title": "RE Processes Overview.png",
    "description": "RE process new\r\n",
    "tags": []
  },
  "df9b027c3bc68b9534c38bb64bb81c2e635920f0.png": {
    "title": "Element 13.png",
    "description": "elicitation",
    "tags": []
  },
  "75c79cac97fc9866e3c7d1133eb9107db965ef7c.png": {
    "title": "Element 16.png",
    "description": "negotiation",
    "tags": []
  },
  "777ba1a0fc7836c0bb30e81adc1b07cc9c5478d9.png": {
    "title": "Element 18.png",
    "description": "documentation",
    "tags": []
  },
  "d6fe4770948e944c5c8fc4a3a48953e5c5134a03.png": {
    "title": "Element 15.png",
    "description": "validation",
    "tags": []
  },
  "e4cbcd72559261c722b8fd110aab29c641d73a3f.png": {
    "title": "Element 14.png",
    "description": "change mgmt",
    "tags": []
  },
  "012684a1163de69fd94b2e3c4247a3086ab61a82.png": {
    "title": "Element 17.png",
    "description": "tracing",
    "tags": []
  },
  "7687b671edd02b14e29fa6cad731140ea866f348.png": {
    "title": "Blocker-13.png",
    "description": "blocker ReEn",
    "tags": []
  },
  "ca989eb73a44ae9c359ea790794f540c65497bfa.png": {
    "title": "System and Context Overview.png",
    "description": "SCO",
    "tags": []
  },
  "ba55768912a7f384aff4c8873b8b3c53189e8bce.png": {
    "title": "Functional Requirements.png",
    "description": "Functional Requirements",
    "tags": []
  },
  "aae0364de065ef49c4004df58aa03194f2ff8c7f.png": {
    "title": "Non Functional Requirements.png",
    "description": "Non Functional Requirements",
    "tags": []
  },
  "2aa0c3fc7f4504999491a9b4ab8e09d046cc3ef0.png": {
    "title": "Techniques Overview.png",
    "description": "technique overview",
    "tags": []
  },
  "570b16e977e3c0c656f8b94d6b68f0b2a02f08dc.png": {
    "title": "elicitation summary.png",
    "description": "summary elicitation",
    "tags": []
  },
  "b1fdc978404ae178a78f3595ff2876e06b5508c3.png": {
    "title": "process-negotiation.png",
    "description": "nego pro",
    "tags": []
  },
  "97ef72aec38a75ec7d11a03a0258ac4af043f029.png": {
    "title": "RE - Lecture title frames-14.png",
    "description": "3.1\r\n",
    "tags": []
  },
  "481928738070e4bd68d78f7eb6c3f3687af1ae04.png": {
    "title": "RE - Lecture title frames-15.png",
    "description": "3.2",
    "tags": []
  },
  "a142439648de7a14b16700c8683d2830229b8a70.png": {
    "title": "lecture overview 2022.png",
    "description": "lectures 2022",
    "tags": []
  }
}